README.md
setup.py
pyiwctl/__init__.py
pyiwctl/wifi_manager.py
pyiwctl.egg-info/PKG-INFO
pyiwctl.egg-info/SOURCES.txt
pyiwctl.egg-info/dependency_links.txt
pyiwctl.egg-info/entry_points.txt
pyiwctl.egg-info/top_level.txt