Metadata-Version: 2.1
Name: pyiwctl
Version: 0.4
Summary: A Python package to manage WiFi connections using iwctl
Home-page: https://github.com/muratozk/pyiwctl
Author: ozkan
Author-email: mozkan.91@gmail.com
Classifier: Programming Language :: Python :: 3
Classifier: License :: OSI Approved :: MIT License
Classifier: Operating System :: OS Independent
Requires-Python: >=3.6
